powermonitor/__init__.py
powermonitor/cli.py
powermonitor/collector/__init__.py
powermonitor/collector/base.py
powermonitor/collector/factory.py
powermonitor/collector/iokit/__init__.py
powermonitor/collector/iokit/bindings.py
powermonitor/collector/iokit/collector.py
powermonitor/collector/iokit/connection.py
powermonitor/collector/iokit/parser.py
powermonitor/collector/iokit/structures.py
powermonitor/collector/ioreg.py
powermonitor/config.py
powermonitor/config_loader.py
powermonitor/database.py
powermonitor/logger.py
powermonitor/models.py
powermonitor/py.typed
powermonitor/tui/__init__.py
powermonitor/tui/app.py
powermonitor/tui/widgets.py
powermonitor-0.0.9.dist-info/WHEEL
powermonitor-0.0.9.dist-info/entry_points.txt
powermonitor-0.0.9.dist-info/METADATA
powermonitor-0.0.9.dist-info/RECORD
