Metadata-Version: 2.3
Name: powermonitor
Version: 0.0.9
Summary: macOS power monitoring tool with auto-updating TUI
Author: narumi
Author-email: narumi <toucans-cutouts0f@icloud.com>
Requires-Dist: loguru>=0.7.3
Requires-Dist: peewee>=3.18.3
Requires-Dist: rich>=13.7.0
Requires-Dist: textual>=0.50.0
Requires-Dist: textual-plotext>=0.2.0
Requires-Dist: typer>=0.21.0
Requires-Python: >=3.13
